README.md
setup.cfg
setup.py
zephony_helpers/__init__.py
zephony_helpers.egg-info/PKG-INFO
zephony_helpers.egg-info/SOURCES.txt
zephony_helpers.egg-info/dependency_links.txt
zephony_helpers.egg-info/requires.txt
zephony_helpers.egg-info/top_level.txt