Metadata-Version: 2.1
Name: zephony-helpers
Version: 0.2
Summary: Helper functions for Python web development
Home-page: https://github.com/Zephony/helpers
Author: Kevin Isaac
Author-email: kevin@zephony.com
Keywords: zephony,helpers,web
